tentacle/__init__.py
tentacle/measurements.py
tentacle/mock.py
tentacle/sensor.py
tentacle/unit.py
tentacle_tentacle-0.0.4.dist-info/LICENSE
tentacle_tentacle-0.0.4.dist-info/METADATA
tentacle_tentacle-0.0.4.dist-info/WHEEL
tentacle_tentacle-0.0.4.dist-info/top_level.txt
tentacle_tentacle-0.0.4.dist-info/RECORD
