Metadata-Version: 2.1
Name: tentacle-tentacle
Version: 0.0.4
Summary: Manage sensors and measurements
Home-page: https://willipink.eu/git/tentacle
Author: Münch Willert
Author-email: moritzmuench@mailbox.org
License: UNKNOWN
Platform: UNKNOWN
Classifier: Programming Language :: Python :: 3
Classifier: License :: OSI Approved :: GNU General Public License v3 (GPLv3)
Classifier: Operating System :: OS Independent
Requires-Python: >=3.7
